pretty_json_loguru/__init__.py
pretty_json_loguru/configure_logger.py
pretty_json_loguru/create_json_formatter.py
pretty_json_loguru/format_traceback.py
pretty_json_loguru-0.3.2.dist-info/METADATA
pretty_json_loguru-0.3.2.dist-info/WHEEL
pretty_json_loguru-0.3.2.dist-info/licenses/LICENSE
pretty_json_loguru-0.3.2.dist-info/RECORD
